[
    {
        "login": "Kirill",
        "password": "rbhbkk2019"
    },
    {
        "login": "sergey",
        "password": "nerfkm3003"
    },
    {
        "login": "SimpleUser",
        "password": "BestPass&Rock'n'Roll"
    },
    {
        "login": "yulia",
        "password": "qwerty"
    },
    {
        "login": "eziz",
        "password": "123456seven"
    },
    {
        "login": "Bac9",
        "password": "345671"
    },
    {
        "login": "alex-margera",
        "password": "reneu12344321"
    },
    {
        "login": "admin",
        "password": "47461031"
    },
    {
        "login": "test",
        "password": "12345678"
    }
]
